cupystorm/__init__.py
cupystorm/cupystorm.icns
cupystorm/turbo_colors.py
cupystorm/turbo_gui.py
cupystorm/turbo_logic.py
cupystorm/turbo_main.py
cupystorm/turbo_simulator.py
cupystorm/turbo_wrapper.py
mannetroll_cupystorm-0.1.1.dist-info/licenses/LICENSE
mannetroll_cupystorm-0.1.1.dist-info/METADATA
mannetroll_cupystorm-0.1.1.dist-info/WHEEL
mannetroll_cupystorm-0.1.1.dist-info/entry_points.txt
mannetroll_cupystorm-0.1.1.dist-info/top_level.txt
mannetroll_cupystorm-0.1.1.dist-info/RECORD
