Metadata-Version: 2.4
Name: mannetroll-cupystorm
Version: 0.1.1
Summary: 2D Turbulence (SciPy + CuPy)
Author: Torbjörn Sjögren
License: MIT License
Requires-Python: <3.14,>=3.13
License-File: LICENSE
Requires-Dist: numpy>=2.3.5
Requires-Dist: pillow>=12.0.0
Requires-Dist: scipy>=1.16.3
Requires-Dist: PySide6>=6.6
Provides-Extra: cuda
Requires-Dist: cupy-cuda13x>=13.6.0; extra == "cuda"
Dynamic: license-file
